sat_datetime/__init__.py
sat_datetime/sat_datetime.py
sat_datetime-1.0.1.dist-info/LICENSE.txt
sat_datetime-1.0.1.dist-info/METADATA
sat_datetime-1.0.1.dist-info/WHEEL
sat_datetime-1.0.1.dist-info/top_level.txt
sat_datetime-1.0.1.dist-info/RECORD
